{
  "url": "https://www.nytimes.com/es/2025/08/08/espanol/america-latina/mexico-trump-ejercito-carteles.html",
  "authorsByline": "Maria Abi-Habib",
  "articleId": "32204ff42f3146af8bf4db6441334ba9",
  "source": {
    "domain": "nytimes.com",
    "paywall": true,
    "location": {
      "country": "us",
      "state": "AZ",
      "county": "Pima County",
      "city": "Tucson",
      "coordinates": {
        "lat": 32.1988848,
        "lon": -110.8218543
      }
    }
  },
  "imageUrl": "https://static01.nyt.com/images/2025/08/08/espanol/08int-mexico-trump-reax-01-lzhp-ES-copy1/08int-mexico-trump-reax-01-lzhp-facebookJumbo.jpg",
  "country": "us",
  "language": "es",
  "pubDate": "2025-08-08T17:36:53.280000+00:00",
  "addDate": "2025-08-08T17:44:53.203787+00:00",
  "refreshDate": "2025-08-08T17:44:53.203789+00:00",
  "score": 1.0,
  "title": "La presidenta de M\u00e9xico dice que las fuerzas militares de EE. UU. no son bienvenidas en su pa\u00eds",
  "description": "La presidenta Sheinbaum neg\u00f3 que EE. UU. vaya a utilizar al ej\u00e9rcito en territorio mexicano, en respuesta a la noticia de que Trump orden\u00f3 al Pent\u00e1gono que atacara a los c\u00e1rteles de la droga.",
  "content": "La presidenta de M\u00e9xico dice que las fuerzas militares de EE. UU. no son bienvenidas en su pa\u00eds La presidenta Sheinbaum neg\u00f3 que EE. UU. vaya a utilizar al ej\u00e9rcito en territorio mexicano, en respuesta a la noticia de que Trump orden\u00f3 al Pent\u00e1gono que atacara a los c\u00e1rteles de la droga. El presidente Donald Trump orden\u00f3 el viernes al Pent\u00e1gono que atacara a los c\u00e1rteles de la droga. Si el Pent\u00e1gono planea desplegar soldados en M\u00e9xico, podr\u00eda tensar los lazos hasta su peor punto en d\u00e9cadas. 8 de agosto de 2025 a las\n\nLa presidenta de M\u00e9xico, Claudia Sheinbaum, neg\u00f3 el viernes que Estados Unidos vaya a utilizar sus fuerzas armadas en territorio mexicano, en respuesta a la noticia de que el presidente Trump hab\u00eda ordenado al Pent\u00e1gono que enfrentara a los c\u00e1rteles de la droga que Estados Unidos considera organizaciones terroristas. \u201cEstados Unidos no va a venir a M\u00e9xico con los militares. Cooperamos, colaboramos, pero no va a haber invasi\u00f3n. Eso est\u00e1 descartado, absolutamente descartado\u201d, dijo. \u201cNi es parte de ning\u00fan acuerdo, ni mucho menos\u201d. Y a\u00f1adi\u00f3: \u201cCuando lo han llegado a plantear, siempre hemos dicho que no\u201d. Sigue sin estar claro qu\u00e9 planes est\u00e1 elaborando el Pent\u00e1gono para una posible acci\u00f3n, y la orden plantea cuestiones jur\u00eddicas sobre varios temas. Los funcionarios mexicanos han rechazado rotundamente, en p\u00fablico y en privado, las sugerencias de una acci\u00f3n militar estadounidense contra los c\u00e1rteles de la droga en territorio mexicano. En su conferencia de prensa matutina, Sheinbaum dijo que leer\u00eda la orden del presidente Trump, pero neg\u00f3 que existiera riesgo alguno de que el ej\u00e9rcito estadounidense pudiera invadir M\u00e9xico. Si el Pent\u00e1gono planea utilizar fuerzas en M\u00e9xico o en cualquier otro lugar de Am\u00e9rica Latina, podr\u00eda tensar los lazos hasta su peor punto en d\u00e9cadas, en un momento en que los pa\u00edses de la regi\u00f3n intentan colaborar estrechamente con Estados Unidos en cuestiones importantes como la migraci\u00f3n y la lucha contra el narcotr\u00e1fico. Dependiendo de lo que haga Estados Unidos, M\u00e9xico podr\u00eda retirar su cooperaci\u00f3n en temas como la seguridad y la migraci\u00f3n si la Casa Blanca act\u00faa unilateralmente, seg\u00fan tres personas familiarizadas con las ideas del gobierno. Estas personas hablaron bajo condici\u00f3n de anonimato para discutir deliberaciones internas delicadas. \u201cNecesitan la cooperaci\u00f3n de M\u00e9xico y necesitan que el Estado y la sociedad mexicanos funcionen. Esto no es Afganist\u00e1n, donde el Estado est\u00e1 roto y puedes hacer lo que quieras porque hay un vac\u00edo\u201d, dijo Arturo Rocha, quien dimiti\u00f3 a finales del a\u00f1o pasado de la Secretar\u00eda de Relaciones Exteriores mexicana, donde se encargaba de las relaciones con Estados Unidos. \u201cEste ha sido siempre el temor m\u00e1s profundo de M\u00e9xico, esta sensaci\u00f3n constante de que podr\u00edamos ser invadidos de nuevo por Estados Unidos\u201d, a\u00f1adi\u00f3. \u201cTendr\u00eda implicaciones importantes en t\u00e9rminos de cooperaci\u00f3n con Estados Unidos en el futuro. La presidenta ha dejado claro que nuestra soberan\u00eda es una l\u00ednea roja\u201d. Las autoridades mexicanas pensaban que hab\u00edan llegado a un punto de inflexi\u00f3n con el gobierno de Trump en la lucha contra el narcotr\u00e1fico, tras haber lanzado una en\u00e9rgica ofensiva contra el C\u00e1rtel de Sinaloa, uno de los mayores productores mundiales de fentanilo. El c\u00e1rtel, uno de los m\u00e1s antiguos y poderosos de M\u00e9xico, ha sufrido graves p\u00e9rdidas mientras Sheinbaum desplegaba cientos de soldados para combatirlo. Miembros de la Marina mexicana vigilan la escena de un crimen a principios de este a\u00f1o. Las autoridades mexicanas han rechazado las sugerencias de una acci\u00f3n militar estadounidense contra los c\u00e1rteles de la droga en territorio mexicano. Los funcionarios estadounidenses parec\u00edan satisfechos con los progresos, y hab\u00edan pregonado un descenso del 50 por ciento en las incautaciones de fentanilo en los \u00faltimos meses en comparaci\u00f3n con los mismos meses del a\u00f1o pasado. No est\u00e1 claro si el descenso se debe a que los c\u00e1rteles se sienten presionados y frenan la producci\u00f3n o a que encuentran formas nuevas e innovadoras de eludir la detecci\u00f3n. El embajador de Estados Unidos en M\u00e9xico, Ronald Johnson, se jact\u00f3 a finales del mes pasado de que el descenso de las incautaciones de fentanilo se deb\u00eda \u201ca una frontera segura\u201d y a una \u201cmayor colaboraci\u00f3n entre Estados Unidos y M\u00e9xico\u201d. Bajo el \u201cliderazgo\u201d de Trump y Sheinbaum, \u201clos c\u00e1rteles est\u00e1n quebrando y nuestros pa\u00edses son m\u00e1s seguros gracias a ello\u201d, dijo Johnson en la plataforma de redes sociales X. Washington tambi\u00e9n ha cooperado con M\u00e9xico en materia de migraci\u00f3n, que alcanz\u00f3 m\u00ednimos hist\u00f3ricos a principios de este a\u00f1o y fue un tema central de las campa\u00f1as presidenciales de Trump. La frontera entre Estados Unidos y M\u00e9xico ha estado tranquila durante el \u00faltimo a\u00f1o, en gran parte porque M\u00e9xico intensific\u00f3 sus esfuerzos para impedir que los migrantes cruzaran su territorio. En junio se registraron los pasos fronterizos m\u00e1s bajos de la historia, seg\u00fan los datos de Aduanas y Protecci\u00f3n Fronteriza, con 6072 migrantes interceptados en la frontera suroeste con M\u00e9xico, frente a los 83.532 del mismo mes de 2024. Si Trump adopta una postura militar estadounidense m\u00e1s agresiva en M\u00e9xico, como el despliegue de soldados estadounidenses o el uso de drones de ataque, podr\u00eda ser pol\u00edticamente desastroso para Sheinbaum. Los mexicanos son extremadamente sensibles al ej\u00e9rcito estadounidense debido a la historia de intervenci\u00f3n, guerra y apropiaci\u00f3n de territorio por parte de Estados Unidos. Sheinbaum ha disfrutado de altos \u00edndices de aprobaci\u00f3n, que rondan el 75 por ciento, pero existen profundas divisiones y competencia por el poder dentro de su partido. Aunque los mexicanos han apoyado sus esfuerzos por negociar con el gobierno de Trump una serie de cuestiones, desde la migraci\u00f3n hasta los aranceles, una acci\u00f3n militar estadounidense dentro de M\u00e9xico probablemente la golpear\u00eda duramente, seg\u00fan los analistas. Tambi\u00e9n podr\u00eda debilitar su capacidad para negociar con Trump sobre futuras cuestiones bilaterales, a\u00f1adieron. El C\u00e1rtel de Sinaloa, uno de los m\u00e1s poderosos de M\u00e9xico, ha sufrido graves p\u00e9rdidas mientras la presidenta Sheinbaum ha desplegado cientos de soldados para combatirlo. La guerra contra el narcotr\u00e1fico en M\u00e9xico ha sido hist\u00f3ricamente liderada por el Departamento de Justicia de Estados Unidos y su agencia antinarc\u00f3ticos, la Administraci\u00f3n para el Control de Drogas. Pero ese esfuerzo se ha llevado a cabo en estrecha colaboraci\u00f3n con las autoridades mexicanas. Y el secretismo en torno a la directiva del Pent\u00e1gono ha suscitado dudas sobre si Estados Unidos podr\u00eda utilizar la fuerza militar de forma unilateral, sin el conocimiento previo de M\u00e9xico, un escenario que podr\u00eda da\u00f1ar la confianza laboriosamente construida entre las autoridades de ambos pa\u00edses. \u201cLos beneficios a corto plazo se ver\u00e1n superados con creces por los costos a largo plazo\u201d, dijo Craig Deare, exagregado militar de la embajada estadounidense en M\u00e9xico en la d\u00e9cada de 1990. \u201cM\u00e9xico ha desconfiado de nosotros durante d\u00e9cadas, y hubo un deshielo en la relaci\u00f3n que comenz\u00f3 en la d\u00e9cada de 1990\u2033, dijo. \u201cEsa desconfianza podr\u00eda volver a surgir ahora\u201d. Deare advirti\u00f3 que hay pocos indicios sobre el tipo de acci\u00f3n que podr\u00eda emprender el ej\u00e9rcito, ya sea al utilizar drones letales o desplegar fuerzas. Estados Unidos ha utilizado durante mucho tiempo drones para hallar redes de producci\u00f3n y contrabando de drogas dentro de M\u00e9xico, pero esos programas encubiertos no estaban autorizados a emprender acciones letales. Funcionarios mexicanos han advertido al gobierno de Trump que los programas de drones letales que Estados Unidos lleva a cabo en lugares como Afganist\u00e1n y Pakist\u00e1n, donde los grupos terroristas suelen ser objetivo de ataques en zonas rurales, se enfrentar\u00edan a circunstancias y riesgos muy diferentes. En M\u00e9xico, los c\u00e1rteles suelen estar arraigados en centros urbanos densamente poblados, lo que aumenta las probabilidades de que se produzcan bajas civiles, y hay muchos m\u00e1s ciudadanos mexicoestadounidenses con doble nacionalidad y sus familiares que viven en lugares que podr\u00edan ser objetivo de ataques. \u201cSi Estados Unidos hace esto sin el consentimiento de M\u00e9xico, la relaci\u00f3n retroceder\u00e1 cien a\u00f1os\u201d, dijo Todd Robinson, quien fue subsecretario de Estado para Asuntos Internacionales de Narc\u00f3ticos y Aplicaci\u00f3n de la Ley en el Departamento de Estado. Dijo que el ej\u00e9rcito estadounidense no tiene las relaciones que otras partes del gobierno estadounidense hab\u00edan desarrollado con las autoridades mexicanas a lo largo de muchos a\u00f1os. \u201cTrabajamos juntos para construir casos, al compartir informaci\u00f3n de inteligencia, eso es lo que construye una relaci\u00f3n a largo plazo\u201d, dijo, y a\u00f1adi\u00f3: \u201cNo hay forma de conseguir una buena relaci\u00f3n si les metes al ej\u00e9rcito estadounidense por la garganta\u201d. Maria Abi-Habib es corresponsal de investigaci\u00f3n radicada en Ciudad de M\u00e9xico y cubre Am\u00e9rica Latina.",
  "medium": "Article",
  "links": [
    "https://www.nytimes.com/es/section/estados-unidos",
    "https://www.nytimes.com/es/section/opinion",
    "https://www.nytimes.com/es/section/negocios",
    "https://www.nytimes.com/es/2025/02/18/espanol/estados-unidos/cia-sobrevuela-mexico-drones.html",
    "https://www.as-coa.org/articles/approval-tracker-mexicos-president-claudia-sheinbaum",
    "https://www.nytimes.com/es/",
    "https://www.nytimes.com/by/maria-abi-habib",
    "https://www.nytimes.com/es/section/cultura",
    "https://www.cbp.gov/newsroom/stats/drug-seizure-statistics",
    "https://www.nytimes.com/es/2025/06/30/espanol/america-latina/cartel-sinaloa-jalisco-alianza-chapo-mayo.html",
    "https://www.nytimes.com/es/section/ciencia-y-tecnologia",
    "https://www.nytimes.com/es/section/america-latina",
    "https://www.nytimes.com/es/2025/08/08/espanol/estados-unidos/trump-carteles-ejercito.html",
    "https://www.nytimes.com/es/section/tiempo-y-clima",
    "https://x.com/USAmbMex/status/1951085207123272145",
    "https://www.cbp.gov/newsroom/stats/nationwide-encounters",
    "https://www.nytimes.com/es/topic/claudia-sheinbaum",
    "https://www.nytimes.com/es/topic/cartel-de-sinaloa",
    "https://www.nytimes.com/es/section/mundo",
    "https://www.nytimes.com/es/section/deportes",
    "https://www.nytimes.com/es/topic/donald-trump",
    "https://www.nytimes.com/es/section/estilos-de-vida",
    "https://www.nytimes.com/2025/08/08/world/americas/mexico-trump-military-cartels.html",
    "https://www.nytimes.com/es/2025/06/30/espanol/america-latina/cartel-sinaloa-mexico-guerra-interna.html",
    "https://www.nytimes.com/es/spotlight/notas-de-bienestar"
  ],
  "labels": [],
  "claim": "",
  "verdict": "",
  "keywords": [
    {
      "name": "United States",
      "weight": 0.08789592
    },
    {
      "name": "Mexico",
      "weight": 0.08322594
    },
    {
      "name": "US military forces",
      "weight": 0.078177266
    },
    {
      "name": "Mexican territory",
      "weight": 0.06830208
    },
    {
      "name": "drug cartels",
      "weight": 0.06739336
    },
    {
      "name": "President Trump",
      "weight": 0.06635104
    },
    {
      "name": "Mexican State",
      "weight": 0.06572376
    },
    {
      "name": "President Donald Trump",
      "weight": 0.06306898
    },
    {
      "name": "President Sheinbaum",
      "weight": 0.063021466
    },
    {
      "name": "Mexican officials",
      "weight": 0.06121653
    }
  ],
  "topics": [],
  "categories": [
    {
      "name": "Politics"
    }
  ],
  "taxonomies": [
    {
      "name": "/News/Politics/Other",
      "score": 0.9873046875
    },
    {
      "name": "/Law & Government/Military/Other",
      "score": 0.9111328125
    },
    {
      "name": "/Law & Government/Government/Executive Branch",
      "score": 0.85107421875
    },
    {
      "name": "/Sensitive Subjects/War & Conflict",
      "score": 0.85107421875
    },
    {
      "name": "/People & Society/Social Sciences/Political Science",
      "score": 0.8330078125
    },
    {
      "name": "/News/World News",
      "score": 0.6962890625
    },
    {
      "name": "/Business & Industrial/Aerospace & Defense/Other",
      "score": 0.391357421875
    }
  ],
  "sentiment": {
    "positive": 0.04156494,
    "negative": 0.73828125,
    "neutral": 0.22045898
  },
  "summary": "",
  "shortSummary": "",
  "translation": "The president of Mexico says that the US military forces are not welcome in her country, President Sheinbaum denied that the US will use the army in Mexican territory, in response to the news that Trump ordered the Pentagon to attack the drug cartels. President Donald Trump ordered the Pentagon to attack the drug cartels. If the Pentagon plans to deploy soldiers in Mexico, could tighten the ties to its worst point in decades. August 8, 2025 at\n\nThe president of Mexico, Claudia Sheinbaum, denied Friday that the United States will use her armed forces in Mexican territory, in response to the news that President Trump had ordered the Pentagon to face the drug cartels that the United States considers terrorist organizations. \"The United States will not come to Mexico with the military. We cooperate, we collaborate, but there will be no invasion. That is discarded, absolutely discarded,\" he said. \"It is not part of any agreement, much less.\" He added: \"When they have come to raise it, we have always said no.\" It still is not clear what plans is preparing the pentagon for a possible action, and the order raises legal issues on various issues. Mexican officials have flatly rejected, in public and private, the suggestions of an American military action against drug cartels in Mexican territory. In his morning press conference, Sheinbaum said he would read the order of President Trump, but denied that there was any risk that the US army could invade Mexico. If the Pentagon plans to use forces in Mexico or anywhere else in Latin America, you could tighten ties until its worst point in decades, at a time when the countries of the region try to collaborate closely with the United States in important issues such as migration and the fight against drug trafficking. Depending on what the United States does, Mexico could withdraw its cooperation on issues such as security and migration if the White House acts unilaterally, according to three people familiar with government ideas. These people spoke about anonymity to discuss delicate internal deliberations. \"They need the cooperation of Mexico and need Mexican State and society to work. This is not Afghanistan, where the State is broken and you can do what you want because there is a vacuum,\" said Arturo Rocha, who resigned at the end of last year of the Mexican Foreign Secretariat, where he was in charge of relations with the United States. \"This has always been the deepest fear of Mexico, this constant feeling that we could be invaded again by the United States,\" he added. \"It would have important implications in terms of cooperation with the United States in the future. The president has made it clear that our sovereignty is a red line.\" The Mexican authorities thought they had reached a turning point with the Trump government in the fight against drug trafficking, after having launched an energetic offensive against the Sinaloa Cartel, one of Fentanil's greatest world producers. The cartel, one of the oldest and most powerful in Mexico, has suffered serious losses while Sheinbaum deployed hundreds of soldiers to fight it. Members of the Mexican Navy watch the scene of a crime earlier this year. The Mexican authorities have rejected the suggestions of an American military action against drug cartels in Mexican territory. American officials seemed satisfied with progress, and had proclaimed a 50 percent decrease in fentanyl seizures in recent months compared to the same months last year. It is not clear if the descent is because the cartels feel pressured and slow down the production or that they find new and innovative ways to avoid detection. The United States ambassador to Mexico, Ronald Johnson, boasted at the end of last month that the decline in fentanyl seizures was \"to a safe border\" and a \"greater collaboration between the United States and Mexico.\" Under the \"leadership\" of Trump and Sheinbaum, \"the cartels are breaking and our countries are safer thanks to this,\" Johnson said on the X. Washington social network. The border between the United States and Mexico has been quiet during the last year, in large part because Mexico intensified its efforts to prevent migrants from crossing their territory. In June, the lowest border crossings in history were recorded, according to customs and border protection data, with 6072 migrants intercepted on the southwest border with Mexico, compared to 83,532 of the same month of 2024. If Trump adopts a more aggressive US military stance in Mexico, such as the deployment of American soldiers or the use of attack drones, it could be politically disastrous for Sheinbaum. Mexicans are extremely sensitive to the US army due to the history of intervention, war and appropriation of territory by the United States. Sheinbaum has enjoyed high approval rates, which are around 75 percent, but there are deep divisions and competition for power within their party. Although Mexicans have supported their efforts to negotiate with the Trump government a series of issues, from migration to tariffs, an American military action within Mexico would probably hit it harshly, according to analysts. He could also weaken his ability to negotiate with Trump on future bilateral issues, they added. The Sinaloa Cartel, one of the most powerful in Mexico, has suffered serious losses while President Sheinbaum has deployed hundreds of soldiers to combat it. The war on drug trafficking in Mexico has historically been led by the United States Department of Justice and its Anti -Narcotics Agency, the Drug Control Administration. But that effort has been carried out in close collaboration with the Mexican authorities. And the secretism around the Pentagon directive has raised doubts about whether the United States could use the military force unilaterally, without the prior knowledge of Mexico, a scenario that could damage confidence laboriously built between the authorities of both countries. \"The short -term benefits will be far exceeded by long -term costs,\" said Craig Deare, an exaggerated military of the US embassy in Mexico in the 1990s. \"Mexico has distrusted us for decades, and there was a thaw in the relationship that began in the 1990 Type of action that the Army could undertake, either by using lethal drones or deploying forces. They are usually the objective of attacks in rural areas, they would face very different circumstances and risks. He will retreat a hundred years, \u201dsaid Todd Robinson, who was Undersecretary of State for International Narcotics Affairs and application of the law in the State Department. He said that the US army does not have the relations that other parts of the US government had developed with the Mexican authorities over many years. \"There is no way to get a good relationship if you put the American army through their throat.\"",
  "translatedTitle": "The president of Mexico says that US military forces are not welcome in her country",
  "translatedDescription": "President Sheinbaum denied that the US will use the army in Mexican territory, in response to the news that Trump ordered the Pentagon to attack the drug cartels.",
  "translatedSummary": "The president of Mexico, Claudia Sheinbaum, has stated that the US military is not welcome in her country and that there will be no invasion. This comes after President Donald Trump ordered the Pentagon to attack the drug cartels. If the Pentagon plans to deploy soldiers in Mexico, this could tighten ties to its worst point in decades. Mexican officials have rejected suggestions of an American military action against drug cartels in Mexican territory. Mexico could withdraw its cooperation on issues such as security and migration if the White House acts unilaterally, according to three people familiar with government ideas. The tensions could negatively impact the future of cooperation between Mexico and the United States. Analysts suggest that an aggressive US military stance could be politically disastrous for Mexico, which is highly sensitive due to its history of intervention by the US.",
  "reprint": false,
  "reprintGroupId": "de8d876d0d444f0d8668d858646addcf",
  "places": [],
  "scraped_sources": [
    {
      "url": "https://www.nytimes.com/by/maria-abi-habib",
      "text": "I am an investigative correspondent for The New York Times reporting on Latin America. I am based in Mexico City.\nWhat I Cover\nI focus on corruption across Latin America, from widespread government rot to the cartels that terrorize civilians in their quest to push drugs across the world. The facts have shown that institutional greed and organized crime have caused many of the region\u2019s most pressing issues, from migration to the drug trade.\nMy Background\nI joined The Times in 2018 in India as a correspondent covering South Asia. In 2021, I moved to Mexico City to become the bureau chief, leading our coverage for Mexico, Central America and the Caribbean.\nI previously worked at The Wall Street Journal where I was a correspondent in Afghanistan from 2010 to 2013. My investigative work in Kabul led to a congressional probe into the conduct of a three-star U.S. general. I was also a roving reporter in the Middle East from 2013 to 2018, covering the Arab Spring and the rise of terror groups that emerged at that time. Before I became a journalist, I studied at Concordia University in Montreal.\nI am a two-time Polk winner for my work in Latin America and the Middle East and a Pulitzer Prize finalist. I also won an Overseas Press Club award for a 2023 investigation into corporate greed and environmental damage in India.\nI grew up in Lebanon and in Washington, D.C., and learned quickly that there are many sides to every story. But my childhood in Roumieh, a small village in Lebanon\u2019s mountains, showed me how big decisions made in Washington can affect the lives of ordinary people thousands of miles away, a topic I\u2019ve chased since.\nMy last name roughly translates to \u201cfather of lovers.\u201d\nJournalistic Ethics\nMy most important duty is to get it right. I pride myself in talking to as many people as possible to represent as many sides of a story as possible. I protect sources who want to remain anonymous for fear of harm or retribution, and I corroborate what people tell me. Accuracy is important and I correct any mistakes.\nContact Me\nYou can email me or reach out on Signal, Twitter or Instagram."
    },
    {
      "url": "https://www.cbp.gov/newsroom/stats/nationwide-encounters",
      "text": "Encounter data includes U.S. Border Patrol (USBP) Title 8 Apprehensions, Office of Field Operations (OFO) Title 8 Inadmissibles, and Title 42 Expulsions. Data is available for the Northern Land Border, Southwest Land Border, and Nationwide (i.e., air, land, and sea modes of transportation) encounters.\nTitle 8 Enforcement Actions refers to apprehensions or inadmissibles processed under CBP\u2019s immigration authority. Inadmissibles refers to individuals encountered at ports of entry (POEs) by OFO who are seeking lawful admission into the United States (U.S.) but are determined to be inadmissible, individuals presenting themselves to seek humanitarian protection under our laws, and individuals who withdraw an application for admission and return to their countries of origin within a short timeframe. Apprehensions refers to the physical control or temporary detainment of a person by USBP between POEs who is not lawfully in the U.S. which may or may not result in an arrest.\nTitle 42 Expulsions refers to individuals encountered by USBP and OFO and expelled to the country of last transit or home country in the interest of public health under Title 42 U.S.C. 265 from March 21, 2020 to May 11, 2023.\nDemographics for USBP and OFO include:\n- Accompanied Minors (AM)\n- Individuals in a Family Unit (FMUA)\n- Single Adults\n- Unaccompanied Alien Children (UAC) / Single Minors\nTo access the data used to build these dashboards, please visit the CBP Data Portal.\nData is extracted from live CBP systems and data sources. Statistical information is subject to change due to corrections, systems changes, change in data definition, additional information, or encounters pending final review. Final statistics are available at the conclusion of each fiscal year.\nU.S. Border Patrol At Large and U.S. Border Patrol at Entry Apprehensions\n| Monthly Totals | Oct-23 | Nov-23 | Dec-23 | Jan-24 | Feb-24 | Mar-24 | Apr-24 | May-24 | Jun-24 | Jul-24 | Aug-24 | Sep-24 | Oct-24 | Nov-24 | Dec-24 | Jan-25 | Feb-25 | Mar-25 | Apr-25 | May- 25 | June-25 |\n|---|---|---|---|---|---|---|---|---|---|---|---|---|---|---|---|---|---|---|---|---|---|\n| Nationwide Total Apprehensions | 190,454 | 192,357 | 251,178 | 125,440 | 142,104 | 139,124 | 131,078 | 121,646 | 87,606 | 59,655 | 60,684 | 55,993 | 58,119 | 47,537 | 48,139 | 30,126 | 9,239 | 8,195 | 10,010 | 10,357 | 8,024 |\n| At Large | 2,977 | 2,668 | 4,676 | 2,057 | 2,670 | 2,700 | 2,813 | 2,429 | 1,800 | 1,432 | 1,655 | 1,609 | 1,652 | 1, 419 | 1,265 | 1,399 | 1,425 | 1,709 | 2,369 | 2,287 | 2,541 |\n| At Entry | 187,477 | 189,689 | 246,502 | 123,383 | 139,434 | 136,424 | 128,265 | 119,217 | 85,806 | 58,223 | 59,029 | 54,384 | 56,467 | 46,118 | 46,874 | 28,727 | 7,814 | 6,486 | 7,641 | 8,070 | 5,483 |\n| Southwest Border Total Apprehensions | 188,749 | 191,106 | 249,740 | 124,215 | 140,641 | 137,473 | 128,895 | 117,905 | 83,532 | 56,400 | 58,009 | 53,858 | 56,519 | 46,612 | 47,323 | 29,105 | 8,348 | 7,183 | 8,378 | 8,723 | 6,072 |\n| At Large | 2,687 | 2,439 | 4,465 | 1,869 | 2,405 | 2,429 | 2,534 | 2,039 | 1,458 | 1,114 | 1,333 | 1,291 | 1,266 | 1,096 | 979 | 937 | 653 | 832 | 894 | 787 | 760 |\n| At Entry | 186,062 | 188,667 | 245,275 | 122,346 | 138,236 | 135,044 | 126,361 | 115,866 | 82,074 | 55,286 | 56,676 | 52,567 | 55,253 | 45,516 | 46,344 | 28,168 | 7,695 | 6,351 | 7,484 | 7,936 | 5,312 |\n| Northern Border Total Apprehensions | 1,522 | 1,148 | 1,178 | 926 | 1,267 | 1,480 | 1,940 | 3,399 | 3,601 | 3,037 | 2,431 | 1,792 | 1,283 | 704 | 510 | 616 | 479 | 504 | 685 | 607 | 703 |\n| At Large | 240 | 189 | 143 | 121 | 182 | 165 | 166 | 221 | 156 | 166 | 180 | 151 | 179 | 157 | 134 | 244 | 393 | 430 | 546 | 497 | 579 |\n| At Entry | 1,282 | 959 | 1,035 | 805 | 1,085 | 1,315 | 1,774 | 3,178 | 3,445 | 2,871 | 2,251 | 1,641 | 1,104 | 547 | 376 | 372 | 86 | 74 | 139 | 110 | 124 |\nAt Entry: Refers to an alien who has entered the United States without admission and has not yet reached his/her destination, regardless of the amount of time since entry.\nAt Large: Refers to an alien who has illegally entered the United States, has already reached their destination, and is encountered or who was legally admitted and has since overstayed their permitted time, illegally remaining in the U.S.\nU.S. Border Patrol and Office of Field Operations Encounters by Area of Responsibility and Component\nNote: Internet Explorer has problems displaying the following charts. Please use another browser (Chrome, Safari, Firefox, Edge) to view. When using a mobile device, the charts are best displayed in landscape mode.\nU.S. Border Patrol and Office of Field Operations Encounters by State\nNote: Nationwide encounters are the sum of CBP encounters across all areas of responsibility including Northern Land Border, Southwest Land Border, OFO non-land border ports of entry (e.g., airports, seaports), and USBP sectors that do not share a land border with Canada or Mexico (e.g., Miami Sector). This data is available for further review and download on the Nationwide Encounters Public Data Portal page.\nU.S. Border Patrol and Office of Field Operations Encounters\nTo ensure that law enforcement sensitive statistics are not publicly released, modifications to data filters have been made that may alter the format of data previously obtained from this dashboard.\nFor additional years of Southwest Land Border encounter data, visit the Southwest Land Border Encounters webpage."
    }
  ],
  "argos_summary": "La presidenta de M\u00e9xico, Claudia Sheinbaum, ha rechazado la posibilidad de que Estados Unidos utilice fuerzas militares en su territorio, en respuesta a la orden del presidente Trump de atacar a los c\u00e1rteles de la droga. Sheinbaum enfatiz\u00f3 que no habr\u00e1 invasi\u00f3n y que la cooperaci\u00f3n entre ambos pa\u00edses se mantendr\u00e1, pero advirti\u00f3 que cualquier acci\u00f3n unilateral de EE. UU. podr\u00eda da\u00f1ar las relaciones bilaterales. La situaci\u00f3n plantea preocupaciones sobre la soberan\u00eda de M\u00e9xico y la confianza en la colaboraci\u00f3n en temas como la migraci\u00f3n y la lucha contra el narcotr\u00e1fico.",
  "argos_id": "4693XL4AP"
}